lightlang/__about__.py
lightlang/__init__.py
lightlang/py.typed
lightlang/abilities/web.py
lightlang/abilities/config/trafilatura.cfg
lightlang/abilities/config/web_config.py
lightlang/llms/llm.py
lightlang/llms/openrouter_llm.py
lightlang/llms/utils.py
lightlang/llms/config/model_config.py
lightlang/llms/config/openrouter_config.py
lightlang/llms/config/provider_config.py
lightlang/prompts/chat_prompt_template.py
lightlang/prompts/prompt_template.py
lightlang/tasks/task.py
lightlang/tasks/task_streaming.py
lightlang/types/__init__.py
lightlang/types/common.py
lightlang/types/models.py
lightlang/types/utils.py
lightlang/utils/algo.py
lightlang/utils/async_utils.py
lightlang/utils/core.py
lightlang/utils/import_utils.py
lightlang/utils/ingest.py
lightlang/utils/log.py
lightlang/utils/output.py
lightlang/utils/strings.py
lightlang/workflows/sequential_workflow.py
lightlang/workflows/workflow_base.py
lightlang/workflows/workflow_data.py
lightlang-0.4.4.dist-info/METADATA
lightlang-0.4.4.dist-info/WHEEL
lightlang-0.4.4.dist-info/licenses/LICENSE
lightlang-0.4.4.dist-info/RECORD
