Metadata-Version: 2.3
Name: lightlang
Version: 0.4.4
Summary: A lightweight ergonomic framework for LLM workflows
Project-URL: Documentation, https://github.com/reasonmethis/lightlang#readme
Project-URL: Issues, https://github.com/reasonmethis/lightlang/issues
Project-URL: Source, https://github.com/reasonmethis/lightlang
Author-email: Dmitriy Vasilyuk <111213624+reasonmethis@users.noreply.github.com>
License-Expression: MIT
License-File: LICENSE
Classifier: Development Status :: 4 - Beta
Classifier: Programming Language :: Python
Classifier: Programming Language :: Python :: 3.11
Classifier: Programming Language :: Python :: 3.12
Classifier: Programming Language :: Python :: Implementation :: CPython
Classifier: Programming Language :: Python :: Implementation :: PyPy
Requires-Python: >=3.11
Requires-Dist: openai~=1.38
Provides-Extra: all
Requires-Dist: aiohttp~=3.10; extra == 'all'
Requires-Dist: beautifulsoup4~=4.12; extra == 'all'
Requires-Dist: certifi>=2024.7.4; extra == 'all'
Requires-Dist: docx2txt~=0.8; extra == 'all'
Requires-Dist: fake-useragent~=1.5; extra == 'all'
Requires-Dist: firecrawl-py~=1.2.3; extra == 'all'
Requires-Dist: google-search-results~=2.4.2; extra == 'all'
Requires-Dist: pydantic~=2.8; extra == 'all'
Requires-Dist: pypdf~=4.3.1; extra == 'all'
Requires-Dist: trafilatura~=1.12.0; extra == 'all'
Provides-Extra: ingest
Requires-Dist: docx2txt~=0.8; extra == 'ingest'
Requires-Dist: pypdf~=4.3.1; extra == 'ingest'
Provides-Extra: web
Requires-Dist: aiohttp~=3.10; extra == 'web'
Requires-Dist: beautifulsoup4~=4.12; extra == 'web'
Requires-Dist: certifi>=2024.7.4; extra == 'web'
Requires-Dist: fake-useragent~=1.5; extra == 'web'
Requires-Dist: firecrawl-py~=1.2.3; extra == 'web'
Requires-Dist: google-search-results~=2.4.2; extra == 'web'
Requires-Dist: pydantic~=2.8; extra == 'web'
Requires-Dist: pypdf~=4.3.1; extra == 'web'
Requires-Dist: trafilatura~=1.12.0; extra == 'web'
